{
  "simulations": [
    {
      "id": "iracing",
      "name": "iRacing",
      "cars": [
        { "id": "ferrari_296_gt3", "name": "Ferrari 296 GT3" },
        { "id": "bmw_m4_gt3", "name": "BMW M4 GT3" },
        { "id": "porsche_911_gt3_r_992", "name": "Porsche 911 GT3 R (992)" },
        { "id": "mercedes_amg_gt3_2020", "name": "Mercedes-AMG GT3 2020" },
        { "id": "audi_r8_lms_evo_ii", "name": "Audi R8 LMS EVO II GT3" },
        { "id": "lamborghini_huracan_gt3_evo", "name": "Lamborghini Huracán GT3 EVO" },
        { "id": "mclaren_720s_gt3_evo", "name": "McLaren 720S GT3 EVO" },
        { "id": "chevrolet_corvette_z06_gt3r", "name": "Chevrolet Corvette Z06 GT3.R" },
        { "id": "ford_mustang_gt3", "name": "Ford Mustang GT3" },
        { "id": "acura_nsx_gt3_evo22", "name": "Acura NSX GT3 EVO 22" },
        { "id": "aston_martin_vantage_gt3", "name": "Aston Martin Vantage GT3" },
        { "id": "lexus_rc_f_gt3", "name": "Lexus RC F GT3" },
        { "id": "cadillac_vseries_r_gtp", "name": "Cadillac V-Series.R GTP" },
        { "id": "acura_arx06_gtp", "name": "Acura ARX-06 GTP" },
        { "id": "bmw_m_hybrid_v8_gtp", "name": "BMW M Hybrid V8 GTP" },
        { "id": "porsche_963_gtp", "name": "Porsche 963 GTP" },
        { "id": "ferrari_499p_gtp", "name": "Ferrari 499P" },
        { "id": "dallara_p217_lmp2", "name": "Dallara P217 LMP2" },
        { "id": "ligier_js_p320_lmp3", "name": "Ligier JS P320 LMP3" }
      ],
      "tracks": [
        { "id": "spa", "name": "Circuit de Spa-Francorchamps" },
        { "id": "monza", "name": "Autodromo Nazionale Monza" },
        { "id": "nurburgring_gp", "name": "Nürburgring Grand-Prix-Strecke" },
        { "id": "nordschleife", "name": "Nürburgring Nordschleife" },
        { "id": "le_mans", "name": "Circuit de la Sarthe (Le Mans)" },
        { "id": "silverstone", "name": "Silverstone Circuit" },
        { "id": "daytona_road", "name": "Daytona International Speedway (Road)" },
        { "id": "sebring", "name": "Sebring International Raceway" },
        { "id": "watkins_glen", "name": "Watkins Glen International" },
        { "id": "road_america", "name": "Road America" },
        { "id": "bathurst", "name": "Mount Panorama Circuit (Bathurst)" },
        { "id": "suzuka", "name": "Suzuka Circuit" },
        { "id": "interlagos", "name": "Autódromo José Carlos Pace (Interlagos)" },
        { "id": "cota", "name": "Circuit of the Americas" },
        { "id": "imola", "name": "Autodromo Enzo e Dino Ferrari (Imola)" },
        { "id": "brands_hatch", "name": "Brands Hatch" },
        { "id": "road_atlanta", "name": "Michelin Raceway Road Atlanta" },
        { "id": "barcelona", "name": "Circuit de Barcelona-Catalunya" },
        { "id": "zandvoort", "name": "Circuit Zandvoort" }
      ]
    },
    {
      "id": "lmu",
      "name": "Le Mans Ultimate",
      "cars": [
        { "id": "ferrari_499p", "name": "Ferrari 499P (Hypercar)" },
        { "id": "toyota_gr010", "name": "Toyota GR010 Hybrid (Hypercar)" },
        { "id": "porsche_963", "name": "Porsche 963 (Hypercar)" },
        { "id": "cadillac_vseries_r", "name": "Cadillac V-Series.R (Hypercar)" },
        { "id": "peugeot_9x8", "name": "Peugeot 9X8 (Hypercar)" },
        { "id": "bmw_m_hybrid_v8", "name": "BMW M Hybrid V8 (Hypercar)" },
        { "id": "glickenhaus_007", "name": "Glickenhaus 007 LMH (Hypercar)" },
        { "id": "alpine_a424", "name": "Alpine A424 (Hypercar)" },
        { "id": "lamborghini_sc63", "name": "Lamborghini SC63 (Hypercar)" },
        { "id": "isotta_fraschini_tipo6", "name": "Isotta Fraschini Tipo 6-C (Hypercar)" },
        { "id": "oreca_07_gibson", "name": "Oreca 07 Gibson (LMP2)" },
        { "id": "ferrari_296_lmgt3", "name": "Ferrari 296 LMGT3" },
        { "id": "porsche_911_gt3_r_lmgt3", "name": "Porsche 911 GT3 R LMGT3" },
        { "id": "aston_martin_vantage_lmgt3", "name": "Aston Martin Vantage AMR LMGT3" },
        { "id": "bmw_m4_lmgt3", "name": "BMW M4 LMGT3" },
        { "id": "corvette_z06_lmgt3", "name": "Chevrolet Corvette Z06 LMGT3.R" },
        { "id": "lamborghini_huracan_lmgt3", "name": "Lamborghini Huracán LMGT3 EVO2" },
        { "id": "mclaren_720s_lmgt3", "name": "McLaren 720S LMGT3 EVO" },
        { "id": "lexus_rc_f_lmgt3", "name": "Lexus RC F LMGT3" },
        { "id": "ford_mustang_lmgt3", "name": "Ford Mustang LMGT3" }
      ],
      "tracks": [
        { "id": "lusail", "name": "Lusail International Circuit (Katar)" },
        { "id": "imola", "name": "Autodromo Enzo e Dino Ferrari (Imola)" },
        { "id": "spa", "name": "Circuit de Spa-Francorchamps" },
        { "id": "le_mans", "name": "Circuit de la Sarthe (Le Mans)" },
        { "id": "interlagos", "name": "Autódromo José Carlos Pace (São Paulo)" },
        { "id": "cota", "name": "Circuit of the Americas" },
        { "id": "fuji", "name": "Fuji Speedway" },
        { "id": "bahrain", "name": "Bahrain International Circuit" },
        { "id": "monza", "name": "Autodromo Nazionale Monza" },
        { "id": "portimao", "name": "Autódromo Internacional do Algarve (Portimão)" },
        { "id": "sebring", "name": "Sebring International Raceway" }
      ]
    },
    {
      "id": "acc",
      "name": "Assetto Corsa Competizione",
      "cars": [
        { "id": "ferrari_296_gt3", "name": "Ferrari 296 GT3" },
        { "id": "bmw_m4_gt3", "name": "BMW M4 GT3" },
        { "id": "porsche_911_gt3_r_992", "name": "Porsche 911 GT3 R (992)" },
        { "id": "lamborghini_huracan_gt3_evo2", "name": "Lamborghini Huracán GT3 EVO2" },
        { "id": "mercedes_amg_gt3_evo", "name": "Mercedes-AMG GT3 2020" },
        { "id": "audi_r8_lms_evo_ii", "name": "Audi R8 LMS EVO II" },
        { "id": "mclaren_720s_gt3_evo", "name": "McLaren 720S GT3 EVO" },
        { "id": "aston_martin_v8_vantage_gt3", "name": "Aston Martin V8 Vantage GT3" },
        { "id": "bentley_continental_gt3_2018", "name": "Bentley Continental GT3 2018" },
        { "id": "honda_nsx_gt3_evo", "name": "Honda NSX GT3 EVO" },
        { "id": "nissan_gtr_nismo_gt3", "name": "Nissan GT-R Nismo GT3" },
        { "id": "lexus_rc_f_gt3", "name": "Lexus RC F GT3" },
        { "id": "bmw_m6_gt3", "name": "BMW M6 GT3" },
        { "id": "porsche_991ii_gt3_r", "name": "Porsche 911 II GT3 R (991.2)" },
        { "id": "ferrari_488_gt3_evo", "name": "Ferrari 488 GT3 EVO" },
        { "id": "lamborghini_huracan_gt3_evo", "name": "Lamborghini Huracán GT3 EVO" }
      ],
      "tracks": [
        { "id": "spa", "name": "Circuit de Spa-Francorchamps" },
        { "id": "monza", "name": "Autodromo Nazionale Monza" },
        { "id": "nurburgring", "name": "Nürburgring Grand-Prix-Strecke" },
        { "id": "nordschleife", "name": "Nürburgring 24h (Nordschleife)" },
        { "id": "zolder", "name": "Circuit Zolder" },
        { "id": "brands_hatch", "name": "Brands Hatch" },
        { "id": "silverstone", "name": "Silverstone Circuit" },
        { "id": "paul_ricard", "name": "Circuit Paul Ricard" },
        { "id": "misano", "name": "Misano World Circuit" },
        { "id": "hungaroring", "name": "Hungaroring" },
        { "id": "zandvoort", "name": "Circuit Zandvoort" },
        { "id": "barcelona", "name": "Circuit de Barcelona-Catalunya" },
        { "id": "kyalami", "name": "Kyalami Grand Prix Circuit" },
        { "id": "mount_panorama", "name": "Mount Panorama Circuit (Bathurst)" },
        { "id": "suzuka", "name": "Suzuka Circuit" },
        { "id": "laguna_seca", "name": "WeatherTech Raceway Laguna Seca" },
        { "id": "imola", "name": "Autodromo Enzo e Dino Ferrari (Imola)" },
        { "id": "oulton_park", "name": "Oulton Park" },
        { "id": "donington", "name": "Donington Park" },
        { "id": "snetterton", "name": "Snetterton Circuit" },
        { "id": "watkins_glen", "name": "Watkins Glen International" },
        { "id": "cota", "name": "Circuit of the Americas" },
        { "id": "indianapolis", "name": "Indianapolis Motor Speedway (Road)" },
        { "id": "valencia", "name": "Circuit Ricardo Tormo (Valencia)" }
      ]
    }
  ]
}
